futures_backends/__init__.py
futures_backends-0.0.1.dist-info/licenses/LICENSE
futures_backends-0.0.1.dist-info/METADATA
futures_backends-0.0.1.dist-info/WHEEL
futures_backends-0.0.1.dist-info/top_level.txt
futures_backends-0.0.1.dist-info/RECORD
