Metadata-Version: 2.4
Name: futures_backends
Version: 0.0.1
Summary: Select the concurrent.futures backend at runtime
Author-email: Jonathan Wright <wright@esrf.fr>
License-Expression: MIT
Project-URL: Homepage, https://github.com/jonwright/futures_backends
Classifier: Programming Language :: Python :: 3
Classifier: Operating System :: OS Independent
Requires-Python: >=2.7
License-File: LICENSE
Dynamic: license-file
